ram/ram.v
// IO legend
// addr_in : the address to be read
// addr_in_manual : manual entry poitn of the address to be read
// program_mode : the switch is to control whether using manual ram loading or
//                running mode, 1 is manual mode
// add_clr : clears the address register
// clk : self explanatory, default clock
// addr_en : Enables the input reading of the address register
// load_manual : Manual load switch used for loading a program into ram
//               manually
// load : Automatic load switch for programming loading itself
// dataout_en : Enables the data to display data on the bus
// data_in_manual : Switches for manualling loading data ** Could be taken out
//                  along with load_manual if hooking it up directly to the
//                  normal load, but I have to think about it
// data : Data is hooked up to the bus directly, rails for reading and writing
//        data in the memory

module ram (
    input [3:0] addr_in,
    input [3:0] addr_in_manual,
    input program_mode, addr_clr, clk, addr_en, load_manual, load, dataout_en,
    input [7:0] data_in_manual,
    inout wire [7:0] data,
    output [7:0] data_out,
    output load_clked
) ;

    // Declare the memory and address register
    reg [7:0] memory [16:0];
    reg [3:0] addr;

    // All the wires for controled by the choice of the program mode swich
    // Write enable is the wire that dictates the writing of the memory
    wire load_en;
    // the final data wire that muxes between the manual and bus data
    wire [7:0] data_in_final;
    // the final address wire that muxes between the manual and bus data
    wire [3:0] addr_in_final;

    // load_clked is the clk edge induced load
    reg load_clked;

    // load_en handler block
    always @(posedge clk) begin
        if (load) begin
            load_clked = 1;
            #1
            load_clked = 0;
        end
        else
            load_clked = 0;
    end

    // sets up IO according to the program mode
    assign load_en = (program_mode) ? load_manual : load_clked;
    assign data_in_final = (program_mode) ? data_in_manual : data;
    assign addr_in_final = (program_mode) ? addr_in_manual : addr;

    // addr_in handler block
    always @(posedge clk) begin
        if (addr_en)
            addr = addr_in;
    end

    always @(*) if (addr_clr) addr = 4'b0;


    // memory handler block
    always @(*)
        if (load_en) memory[addr_in_final] = data_in_final;

    assign data = (dataout_en) ? memory[addr_in_final] : 8'bz;
    assign data_out = memory[addr_in_final];

endmodule

ram/ram_tb.v
module ram_tb ();

    reg [3:0] addr_in, addr_in_manual;
    reg program_mode, addr_clr, clk, addr_en, load_manual, load, dataout_en;
    reg [7:0] data_in_manual;
    wire [7:0] data;
    reg [7:0] data_in;
    wire [7:0] data_out;
    wire [7:0] memory;
    wire load_clked;

    assign data = (dataout_en) ? 8'hz : data_in;
    assign data_out = data;
    ram inst (addr_in, addr_in_manual, program_mode, addr_clr, clk, addr_en, load_manual, load, dataout_en, data_in_manual, data, memory, load_clked);

    initial begin
        clk = 0;
        repeat(50) #5 clk = ~clk;
    end

    initial begin
        // test manual entry mode first
        program_mode = 1;
        load_manual = 0;
        dataout_en = 0;
        data_in_manual = 0;
        addr_in_manual = 0;
        addr_clr = 0;
        #5
        data_in_manual = 8'ha;
        #1
        load_manual = 1;
        #1
        load_manual = 0;
        dataout_en = 1;
        #1
        addr_in_manual = 4'b0001;
        #1
        data_in_manual = 8'h1b;
        load_manual = 1;
        #1
        load_manual = 0;
        #1
        addr_in_manual = 4'b0;

        #10
        // Test automatic mode
        program_mode = 0;
        addr_en = 0;
        dataout_en = 0;
        load = 0;
        #1
        addr_in = 4'b1010;
        #5
        addr_en = 1;
        #5
        data_in = 8'haa;
        #1
        load = 1;
        #5
        load = 0;
        #10
        data_in = 8'hz;
        #5
        dataout_en = 1;
        #5
        addr_en = 0;
        #5
        addr_in = 4'b0001;
        #5
        addr_en = 1;
        #10
        addr_en = 0;
        #10
        addr_clr = 1;
        #1
        addr_clr = 0;
        #10
        addr_en = 1;

    end

    initial
        $dumpvars(0, addr_in, addr_in_manual, program_mode, addr_clr, clk, addr_en, load_manual, load, dataout_en, data_in_manual, data, data_in, data_out, memory, load_clked);

endmodule

ram/ram.vcd
$date
	Sat Jun  5 19:57:26 2021
$end
$version
	Icarus Verilog
$end
$timescale
	1s
$end
$scope module ram_tb $end
$var reg 4 ! addr_in [3:0] $end
$upscope $end
$scope module ram_tb $end
$var reg 4 " addr_in_manual [3:0] $end
$upscope $end
$scope module ram_tb $end
$var reg 1 # program_mode $end
$upscope $end
$scope module ram_tb $end
$var reg 1 $ addr_clr $end
$upscope $end
$scope module ram_tb $end
$var reg 1 % clk $end
$upscope $end
$scope module ram_tb $end
$var reg 1 & addr_en $end
$upscope $end
$scope module ram_tb $end
$var reg 1 ' load_manual $end
$upscope $end
$scope module ram_tb $end
$var reg 1 ( load $end
$upscope $end
$scope module ram_tb $end
$var reg 1 ) dataout_en $end
$upscope $end
$scope module ram_tb $end
$var reg 8 * data_in_manual [7:0] $end
$upscope $end
$scope module ram_tb $end
$var wire 8 + data [7:0] $end
$upscope $end
$scope module ram_tb $end
$var reg 8 , data_in [7:0] $end
$upscope $end
$scope module ram_tb $end
$var wire 8 - data_out [7:0] $end
$upscope $end
$scope module ram_tb $end
$var wire 8 . memory [7:0] $end
$upscope $end
$scope module ram_tb $end
$var wire 1 / load_clked $end
$upscope $end
$enddefinitions $end
#0
$dumpvars
x/
bx .
bx -
bx ,
bx +
b0 *
0)
x(
0'
x&
0%
0$
1#
b0 "
bx !
$end
#5
0/
b1010 *
1%
#6
b1010 .
1'
#7
b1010 -
b1010 +
1)
0'
#8
bx -
bx +
bx .
b1 "
#9
b11011 -
b11011 +
b11011 .
1'
b11011 *
#10
0'
0%
#11
b1010 -
b1010 +
b1010 .
b0 "
#15
1%
#20
0%
#21
bx -
bx +
bx .
0(
0)
0&
0#
#22
b1010 !
#25
1%
#27
1&
#30
0%
#32
b10101010 -
b10101010 +
b10101010 ,
#33
1(
#35
b10101010 .
1/
1%
#36
0/
#38
0(
#40
0%
#45
1%
#48
bz -
bz +
bz ,
#50
0%
#53
b10101010 -
b10101010 +
1)
#55
1%
#58
0&
#60
0%
#63
b1 !
#65
1%
#68
1&
#70
0%
#75
b11011 -
b11011 +
b11011 .
1%
#78
0&
#80
0%
#85
1%
#88
b1010 -
b1010 +
b1010 .
1$
#89
0$
#90
0%
#95
1%
#99
1&
#100
0%
#105
b11011 -
b11011 +
b11011 .
1%
