register_8/register_8.v
module register_8 (
    input clk, clr, en, load,
    input [7:0] data_in,
    output reg [7:0] data_out
);

    reg [7:0] data;

    always @(posedge clk) begin
        if (en) begin
            if (clr)
                data = 8'b0;
            else if (load)
                data = data_in;
            data_out = data;
        end
        else
            data_out = 8'bz;
    end


endmodule

register_8/register_8_tb.v
module register_8_tb ();

    reg clk, clr, en, load;
    reg [7:0] data_in;
    wire [7:0] data_out;

    register_8 inst (clk, clr, en, load, data_in, data_out);

    initial begin
        clk = 0;
        repeat(50) #5 clk = ~clk;
    end

    initial begin
        load = 1;
        en = 1;
        data_in = 8'd255;
        clr = 0;
        #10 load = 0;
        #10 data_in = 0;
        #10 en = 0;
        #10 en = 1;
        #10 clr = 1;
        #10 clr = 0;

    end

    initial
        $dumpvars(0, clk, clr, en, load, data_in, data_out);

endmodule

register_8/register_8.vcd
$date
	Wed Mar  3 21:46:32 2021
$end
$version
	Icarus Verilog
$end
$timescale
	1s
$end
$scope module register_8_tb $end
$var reg 1 ! clk $end
$upscope $end
$scope module register_8_tb $end
$var reg 1 " clr $end
$upscope $end
$scope module register_8_tb $end
$var reg 1 # en $end
$upscope $end
$scope module register_8_tb $end
$var reg 1 $ load $end
$upscope $end
$scope module register_8_tb $end
$var reg 8 % data_in [7:0] $end
$upscope $end
$scope module register_8_tb $end
$var wire 8 & data_out [7:0] $end
$upscope $end
$enddefinitions $end
#0
$dumpvars
bx &
b11111111 %
1$
1#
0"
0!
$end
#5
b11111111 &
1!
#10
0!
0$
#15
1!
#20
0!
b0 %
#25
1!
#30
0!
0#
#35
bz &
1!
#40
0!
1#
#45
b11111111 &
1!
#50
0!
1"
#55
b0 &
1!
#60
0!
0"
