alu/alu.v
module alu(
    input [7:0] a, b,
    input sub, en, flag_clk, flag_clr, flag_en,
    output reg [7:0] ans, 
    output reg carry, is_zero
);

    integer ans_wcarry;

    always @(*) begin
        case (sub)
            1 : ans_wcarry = a - b;
            0 : ans_wcarry = a + b;
        endcase

        if (en)
            ans = ans_wcarry[7:0];
        else
            ans = 8'bz;
    end

    always @(posedge flag_clk or posedge flag_clr) begin
        if (flag_clr) begin
            carry = 0;
            is_zero = 0;
        end
        else if (flag_en) begin
            carry = ans_wcarry[8];
            is_zero = (ans_wcarry  == 0);
        end
    end

endmodule

alu/alu_tb.v
module alu_tb();

    reg [7:0] a, b;
    reg sub, en, clk, clr, flag_en;
    wire [7:0] ans;
    wire carry, is_zero;

    alu inst (a, b, sub, en, clk, clr, flag_en, ans, carry, is_zero);

    initial begin
        $dumpvars(0, a, b, sub, en, clk, clr, flag_en, ans, carry, is_zero);
    end

    initial begin
        clk = 0;
        repeat(50) #5 clk = ~clk;
    end

    initial begin
        en = 0;
        sub = 0;
        a = 8'd20;
        b = 8'd10;
        flag_en = 1;
        clr = 0;
        #10 en = 1;
        #10 en = 0;
        #10 en = 1;
        #1 sub = 1;
        #10
        a = 8'd10;
        b = 8'd20;
        #10
        a = 8'd20;
        b = 8'd20;
        #5
        flag_en = 0;
        a = 8'd127;
        b = 8'd127;
        sub = 0;
        #10
        flag_en = 1;
        #10
        clr = 1;
    end
endmodule

alu/alu.vcd
$date
	Mon Mar 15 20:51:43 2021
$end
$version
	Icarus Verilog
$end
$timescale
	1s
$end
$scope module alu_tb $end
$var reg 8 ! a [7:0] $end
$upscope $end
$scope module alu_tb $end
$var reg 8 " b [7:0] $end
$upscope $end
$scope module alu_tb $end
$var reg 1 # sub $end
$upscope $end
$scope module alu_tb $end
$var reg 1 $ en $end
$upscope $end
$scope module alu_tb $end
$var reg 1 % clk $end
$upscope $end
$scope module alu_tb $end
$var reg 1 & clr $end
$upscope $end
$scope module alu_tb $end
$var reg 1 ' flag_en $end
$upscope $end
$scope module alu_tb $end
$var wire 8 ( ans [7:0] $end
$upscope $end
$scope module alu_tb $end
$var wire 1 ) carry $end
$upscope $end
$scope module alu_tb $end
$var wire 1 * is_zero $end
$upscope $end
$enddefinitions $end
#0
$dumpvars
x*
x)
bz (
1'
0&
0%
0$
0#
b1010 "
b10100 !
$end
#5
0*
0)
1%
#10
b11110 (
0%
1$
#15
1%
#20
bz (
0%
0$
#25
1%
#30
b11110 (
0%
1$
#31
b1010 (
1#
#35
1%
#40
0%
#41
b11110110 (
b10100 "
b1010 !
#45
1)
1%
#50
0%
#51
b0 (
b10100 !
#55
1*
0)
1%
#56
b11111110 (
0#
b1111111 "
b1111111 !
0'
#60
0%
#65
1%
#66
1'
#70
0%
#75
0*
1%
#76
1&
